pyns/__init__.py
pyns/api.py
pyns/fetch_utils.py
pyns/endpoints/__init__.py
pyns/endpoints/analysis.py
pyns/endpoints/base.py
pyns/endpoints/dataset.py
pyns/endpoints/predictor.py
pyns/endpoints/user.py
pyns/endpoints/utils.py
tests/__init__.py
tests/conftest.py
tests/test_analysis.py
tests/test_client.py
tests/test_dataset.py
tests/test_predictor.py
tests/test_run.py
tests/test_user.py
pyns-0.5.1.dist-info/LICENSE
pyns-0.5.1.dist-info/METADATA
pyns-0.5.1.dist-info/WHEEL
pyns-0.5.1.dist-info/top_level.txt
pyns-0.5.1.dist-info/RECORD
