Metadata-Version: 2.1
Name: pyns
Version: 0.5.1
Summary: Neuroscout API wrapper
Home-page: http://github.com/neuroscout/pyns
Author: Alejandro de la Vega
Author-email: aleph4@gmail.com
License: MIT
Platform: UNKNOWN
Classifier: Programming Language :: Python :: 3
Classifier: License :: OSI Approved :: MIT License
Classifier: Operating System :: OS Independent
